{"note":"Don't delete this file! It's used internally to help with page regeneration.","name":"APiDo","google":"UA-32909211-1","tagline":"Réalisation de vos projets avec plaisir et agilité","body":"### Vous avez un projet de développement ?\r\nAPiDo met à votre service son savoir faire en développement de projet agile.\r\n\r\n```\r\nDévelopper est notre plaisir; votre succès notre satisfaction.\r\n```\r\n\r\n### Vous avez besoin d'accompagnement pour gérer votre projet ?\r\nAPiDo cultive les bonnes méthodes de gestion de projet agile avec SCRUM et eXtreme Programming.\r\nToutefois, ces méthodes ne peuvent pas être intégralement adoptées dans toutes les structures.\r\n\r\n```\r\nNous vous accompagnons dans la mise en place des méthodes qui vous conviennent.\r\n```\r\n\r\n### Vous avez besoin de formation AGILE, SCRUM et XP pour vos équipes de développement ?\r\nAPiDo anime des sessions de formation à la carte de 1 à 3 jours pour les développeurs, chefs de projets et managers.\r\nAppelez-nous, nous vous conseillerons dans le format le plus adapté en fonction de vos attentes."}